[
  { "id": 0, "name": "Contract #0", "customerId": 0 },
  { "id": 0, "name": "Contract #1", "customerId": 1 },
  { "id": 0, "name": "Contract #2", "customerId": 0 },
  { "id": 0, "name": "Contract #3", "customerId": 1 },
  { "id": 0, "name": "Contract #4", "customerId": 0 },
  { "id": 0, "name": "Contract #5", "customerId": 1 },
  { "id": 0, "name": "Contract #6", "customerId": 0 },
  { "id": 0, "name": "Contract #7", "customerId": 1 },
  { "id": 0, "name": "Contract #8", "customerId": 0 },
  { "id": 0, "name": "Contract #9", "customerId": 1 },
  { "id": 0, "name": "Contract #10", "customerId": 0 },
  { "id": 0, "name": "Contract #11", "customerId": 1 },
  { "id": 0, "name": "Contract #12", "customerId": 0 },
  { "id": 0, "name": "Contract #13", "customerId": 1 },
  { "id": 0, "name": "Contract #14", "customerId": 0 },
  { "id": 0, "name": "Contract #15", "customerId": 1 },
  { "id": 0, "name": "Contract #16", "customerId": 0 },
  { "id": 0, "name": "Contract #17", "customerId": 1 },
  { "id": 0, "name": "Contract #18", "customerId": 0 },
  { "id": 0, "name": "Contract #19", "customerId": 1 },
  { "id": 0, "name": "Contract #20", "customerId": 0 },
  { "id": 0, "name": "Contract #21", "customerId": 1 },
  { "id": 0, "name": "Contract #22", "customerId": 0 },
  { "id": 0, "name": "Contract #23", "customerId": 1 },
  { "id": 0, "name": "Contract #24", "customerId": 0 },
  { "id": 0, "name": "Contract #25", "customerId": 1 }
]
